{
  "$schema": "https://raw.githubusercontent.com/jsonresume/resume-schema/v1.0.0/schema.json",
  "basics": {
    "name": "Jane Doe",
    "label": "Your Title Here",
    "email": "youremail@institution.edu",
    "url": "https://your-website.com",
    "summary": "Write a brief professional summary here. This appears at the top of your CV and should capture the essence of your academic identity. Mention your research focus, key achievements, and what drives your work. Keep it concise but compelling—think of it as your academic elevator pitch.",
    "location": {
      "city": "Your City",
      "countryCode": "US"
    },
    "profiles": [
      {
        "network": "Your Institution",
        "url": "https://your-institution.edu"
      }
    ]
  },
  "education": [
    {
      "institution": "University of Somewhere",
      "url": "https://www.university.edu",
      "area": "Your Field",
      "studyType": "PhD",
      "startDate": "2018",
      "endDate": "2023",
      "thesis": "Your Dissertation Title Goes Here",
      "honors": "Any honors or distinctions"
    },
    {
      "institution": "Another University",
      "url": "https://www.another-university.edu",
      "area": "Related Field",
      "studyType": "MSc",
      "startDate": "2016",
      "endDate": "2018",
      "honors": "With distinction"
    },
    {
      "institution": "Your Undergraduate Institution",
      "url": "https://www.undergrad.edu",
      "area": "Foundational Field",
      "studyType": "BSc",
      "startDate": "2012",
      "endDate": "2016",
      "honors": "First Class Honours"
    }
  ],
  "work": [
    {
      "name": "Current Institution",
      "position": "Your Current Position",
      "url": "https://www.current-institution.edu",
      "startDate": "2023",
      "endDate": "present",
      "summary": "Brief description of your current role and responsibilities"
    },
    {
      "name": "Previous Institution",
      "position": "Previous Position",
      "url": "https://www.previous-institution.edu",
      "startDate": "2020",
      "endDate": "2023",
      "summary": "What you did in this role"
    },
    {
      "name": "Research Lab or Company",
      "position": "Research Intern/Assistant",
      "startDate": "2019",
      "endDate": "2020",
      "summary": "Description of research or work conducted"
    }
  ],
  "awards": [
    {
      "title": "Best Paper Award",
      "date": "2023",
      "awarder": "Conference Name",
      "summary": "Brief description of the award"
    },
    {
      "title": "Research Fellowship",
      "date": "2022",
      "awarder": "Funding Agency",
      "summary": "Description of the fellowship"
    },
    {
      "title": "Graduate Prize",
      "date": "2018",
      "awarder": "University Name"
    }
  ],
  "publications": [
    {
      "name": "Your Paper Title",
      "publisher": "Journal or Conference Name",
      "releaseDate": "2023",
      "summary": "Brief description of the publication"
    },
    {
      "name": "Another Publication",
      "publisher": "Another Venue",
      "releaseDate": "2022"
    }
  ],
  "skills": [
    {
      "name": "Research Methods",
      "keywords": ["Method 1", "Method 2", "Method 3", "Method 4"]
    },
    {
      "name": "Technical Skills",
      "keywords": ["Skill 1", "Skill 2", "Skill 3", "Skill 4"]
    }
  ],
  "languages": [
    {
      "language": "English",
      "fluency": "Native"
    },
    {
      "language": "Another Language",
      "fluency": "Proficient"
    }
  ],
  "interests": [
    {
      "name": "Your Interests",
      "keywords": ["Interest 1", "Interest 2"]
    }
  ],
  "references": [
    {
      "name": "Prof. Reference One",
      "reference": "Institution, Department"
    },
    {
      "name": "Prof. Reference Two",
      "reference": "Institution, Department"
    }
  ],
  "meta": {
    "canonical": "https://jsonresume.org/schema/",
    "version": "v1.0.0",
    "lastModified": "2024-01-01"
  }
}
